pytest_drop_dup_tests.py
pytest_drop_dup_tests-1.0.0.dist-info/LICENSE
pytest_drop_dup_tests-1.0.0.dist-info/METADATA
pytest_drop_dup_tests-1.0.0.dist-info/WHEEL
pytest_drop_dup_tests-1.0.0.dist-info/entry_points.txt
pytest_drop_dup_tests-1.0.0.dist-info/top_level.txt
pytest_drop_dup_tests-1.0.0.dist-info/RECORD
