Metadata-Version: 2.1
Name: pytest-drop-dup-tests
Version: 1.0.0
Summary: A Pytest plugin to drop duplicated tests during collection
Home-page: https://github.com/nicoddemus/pytest-drop-dup-tests
Author: Bruno Oliveira
Author-email: nicoddemus@gmail.com
Maintainer: Bruno Oliveira
Maintainer-email: nicoddemus@gmail.com
License: MIT
Classifier: Development Status :: 5 - Production/Stable
Classifier: Framework :: Pytest
Classifier: Intended Audience :: Developers
Classifier: Topic :: Software Development :: Testing
Classifier: Programming Language :: Python
Classifier: Programming Language :: Python :: 3.8
Classifier: Programming Language :: Python :: 3.9
Classifier: Programming Language :: Python :: 3.10
Classifier: Programming Language :: Python :: 3.11
Classifier: Programming Language :: Python :: 3.12
Classifier: Programming Language :: Python :: Implementation :: CPython
Classifier: Operating System :: OS Independent
Classifier: License :: OSI Approved :: MIT License
License-File: LICENSE
Requires-Dist: pytest >=7
